MANIFEST.in
README.md
setup.py
view.png
Ginobifold/__init__.py
Ginobifold/configs.py
Ginobifold/import_weight.py
Ginobifold/predict.py
Ginobifold/residue_constants.py
Ginobifold/residue_torch_constants.py
Ginobifold.egg-info/PKG-INFO
Ginobifold.egg-info/SOURCES.txt
Ginobifold.egg-info/dependency_links.txt
Ginobifold.egg-info/top_level.txt
Ginobifold/featurizer/__init__.py
Ginobifold/featurizer/feature_transform.py
Ginobifold/model/__init__.py
Ginobifold/model/_base2.py
Ginobifold/model/_fast_softmax.py
Ginobifold/model/base.py
Ginobifold/model/blocks.py
Ginobifold/model/feature_embedder.py
Ginobifold/model/heads.py
Ginobifold/model/stacks.py
Ginobifold/model/structure_module.py
Ginobifold/openfold/__init__.py
Ginobifold/openfold/config.py
Ginobifold/openfold/openfold_feats.py
Ginobifold/openfold/data/__init__.py
Ginobifold/openfold/data/data_modules.py
Ginobifold/openfold/data/data_pipeline.py
Ginobifold/openfold/data/data_transforms.py
Ginobifold/openfold/data/errors.py
Ginobifold/openfold/data/feature_pipeline.py
Ginobifold/openfold/data/input_pipeline.py
Ginobifold/openfold/data/mmcif_parsing.py
Ginobifold/openfold/data/parsers.py
Ginobifold/openfold/data/templates.py
Ginobifold/openfold/data/tools/__init__.py
Ginobifold/openfold/data/tools/hhblits.py
Ginobifold/openfold/data/tools/hhsearch.py
Ginobifold/openfold/data/tools/jackhmmer.py
Ginobifold/openfold/data/tools/kalign.py
Ginobifold/openfold/data/tools/utils.py
Ginobifold/openfold/np/__init__.py
Ginobifold/openfold/np/protein.py
Ginobifold/openfold/np/residue_constants.py
Ginobifold/openfold/np/relax/__init__.py
Ginobifold/openfold/np/relax/amber_minimize.py
Ginobifold/openfold/np/relax/cleanup.py
Ginobifold/openfold/np/relax/relax.py
Ginobifold/openfold/np/relax/utils.py
Ginobifold/openfold/utils/__init__.py
Ginobifold/openfold/utils/argparse.py
Ginobifold/openfold/utils/callbacks.py
Ginobifold/openfold/utils/checkpointing.py
Ginobifold/openfold/utils/chunk_utils.py
Ginobifold/openfold/utils/exponential_moving_average.py
Ginobifold/openfold/utils/feats.py
Ginobifold/openfold/utils/import_weights.py
Ginobifold/openfold/utils/logger.py
