Metadata-Version: 2.1
Name: Ginobifold
Version: 0.1.2
Summary: Simplified Af2 inference code
Author: Kexin Zhang
Author-email: zhangkx2022@shanghaitech.edu.cn
License: MIT
Keywords: computational biology,protein
Platform: UNKNOWN
Classifier: Programming Language :: Python :: 3
Classifier: Topic :: Scientific/Engineering
